LICENSE
README.md
setup.cfg
setup.py
src/xgbauto/__init__.py
src/xgbauto/api.py
src/xgbauto/autoxgb.py
src/xgbauto/enums.py
src/xgbauto/logger.py
src/xgbauto/metrics.py
src/xgbauto/params.py
src/xgbauto/predict.py
src/xgbauto/schemas.py
src/xgbauto/utils.py
src/xgbauto.egg-info/PKG-INFO
src/xgbauto.egg-info/SOURCES.txt
src/xgbauto.egg-info/dependency_links.txt
src/xgbauto.egg-info/entry_points.txt
src/xgbauto.egg-info/requires.txt
src/xgbauto.egg-info/top_level.txt
src/xgbauto/cli/__init__.py
src/xgbauto/cli/autoxgb.py
src/xgbauto/cli/predict.py
src/xgbauto/cli/serve.py
src/xgbauto/cli/train.py