Metadata-Version: 2.1
Name: xgbauto
Version: 1.0.1
Summary: xgbauto: tuning xgboost with optuna
Home-page: https://github.com/parikhprakash/xgbauto
Author: Prakash Parikh
Author-email: parikhprakash@gmail.com
License: Apache 2.0
Platform: linux
Platform: unix
Requires-Python: >=3.6
License-File: LICENSE
